odoo/addons/website_sale_checkout_country_vat/README.rst
odoo/addons/website_sale_checkout_country_vat/__init__.py
odoo/addons/website_sale_checkout_country_vat/__manifest__.py
odoo/addons/website_sale_checkout_country_vat/i18n/es.po
odoo/addons/website_sale_checkout_country_vat/i18n/website_sale_checkout_country_vat.pot
odoo/addons/website_sale_checkout_country_vat/readme/CONFIGURE.rst
odoo/addons/website_sale_checkout_country_vat/readme/CONTRIBUTORS.rst
odoo/addons/website_sale_checkout_country_vat/readme/DESCRIPTION.rst
odoo/addons/website_sale_checkout_country_vat/readme/USAGE.rst
odoo/addons/website_sale_checkout_country_vat/static/description/icon.png
odoo/addons/website_sale_checkout_country_vat/static/description/index.html
odoo/addons/website_sale_checkout_country_vat/static/src/js/dropdown.js
odoo/addons/website_sale_checkout_country_vat/views/assets.xml
odoo/addons/website_sale_checkout_country_vat/views/templates.xml
odoo12_addon_website_sale_checkout_country_vat-12.0.1.2.0.dist-info/METADATA
odoo12_addon_website_sale_checkout_country_vat-12.0.1.2.0.dist-info/WHEEL
odoo12_addon_website_sale_checkout_country_vat-12.0.1.2.0.dist-info/top_level.txt
odoo12_addon_website_sale_checkout_country_vat-12.0.1.2.0.dist-info/RECORD
