Metadata-Version: 2.1
Name: odoo12-addon-website-sale-checkout-country-vat
Version: 12.0.1.2.0
Summary: Autocomplete VAT in checkout process
Home-page: https://www.tecnativa.com
Author: Tecnativa, Odoo Community Association (OCA)
Author-email: support@odoo-community.org
License: LGPL-3
Platform: UNKNOWN
Classifier: Programming Language :: Python
Classifier: Framework :: Odoo
Classifier: License :: OSI Approved :: GNU Lesser General Public License v3 (LGPLv3)
Requires-Python: >=3.5
Requires-Dist: odoo12-addon-website-snippet-country-dropdown
Requires-Dist: odoo (<12.1dev,>=12.0a)
